<?xml version = '1.0' encoding = 'UTF-8'?>
<Relation class="oracle.dbtools.crest.model.design.logical.Relation" name="servicio_spa" directorySegmentName="seg_0" id="8918FBE3-9C3E-2AEC-D8A9-EA619F8FD675">
<createdBy>juanroj</createdBy>
<createdTime>2023-09-27 23:23:24 UTC</createdTime>
<ownerDesignName>C1-P1-Sistrans</ownerDesignName>
<engineerTo>
<item key="98C83986-CDB6-4E63-3D26-988371A9968F" value="true"/>
</engineerTo>
<sourcePk>C11CCADB-AB9D-7A04-9967-8C44A669BC97</sourcePk>
<identifying>true</identifying>
<optionalSource>false</optionalSource>
<optionalTarget>false</optionalTarget>
<sourceCardinality>1</sourceCardinality>
<sourceEntity>E22C8B2D-09CE-0BE7-D3EB-67B511D3DC33</sourceEntity>
<targetCardinalityString>*</targetCardinalityString>
<targetEntity>B08DFA27-0BA8-5570-E060-298144872710</targetEntity>
<transferable>true</transferable>
<deleteRule>NO ACTION</deleteRule>
</Relation>